rembgpy/__init__.py
rembgpy/bg.py
rembgpy-1.0.1.dist-info/METADATA
rembgpy-1.0.1.dist-info/WHEEL
rembgpy-1.0.1.dist-info/top_level.txt
rembgpy-1.0.1.dist-info/RECORD
