Metadata-Version: 2.1
Name: rembgpy
Version: 1.0.1
Summary: A simple python api wrapper for remove.bg.
Home-page: https://github.com/jiroawesome/rembgpy
Author: jiroawesome
License: UNKNOWN
Project-URL: Bug Tracker, https://github.com/jiroawesome/rembgpy/issues
Platform: UNKNOWN
Classifier: Programming Language :: Python :: 3
Classifier: License :: OSI Approved :: MIT License
Classifier: Operating System :: OS Independent
Requires-Python: >=3.6
Requires-Dist: requests
